veriservice/__init__.py
veriservice/veriservice_pb2.py
veriservice/veriservice_pb2_grpc.py
veriservice-0.0.34.dist-info/LICENSE.txt
veriservice-0.0.34.dist-info/METADATA
veriservice-0.0.34.dist-info/WHEEL
veriservice-0.0.34.dist-info/top_level.txt
veriservice-0.0.34.dist-info/RECORD
