Metadata-Version: 2.1
Name: veriservice
Version: 0.0.34
Summary: Python client for Veri
Home-page: http://github.com/bgokden/veri-python-client
Author: Berk Gokden
Author-email: berkgokden@gmail.com
License: Apache Software License
Keywords: veri service python client
Platform: UNKNOWN
Requires-Dist: grpcio-tools
Requires-Dist: googleapis-common-protos
